npy_append_array/__init__.py
npy_append_array/format.py
npy_append_array/npy_append_array.py
npy_append_array-0.9.18.dist-info/licenses/LICENSE
npy_append_array-0.9.18.dist-info/METADATA
npy_append_array-0.9.18.dist-info/WHEEL
npy_append_array-0.9.18.dist-info/top_level.txt
npy_append_array-0.9.18.dist-info/RECORD
