Metadata-Version: 2.4
Name: npy-append-array
Version: 0.9.18
Summary: Create Numpy .npy files by appending on the growth axis
Author: Michael Siebert, Joshua Adelman, Yoav Git
Maintainer-email: Michael Siebert <michael.siebert2k@gmail.com>
License-Expression: MIT
Project-URL: Homepage, https://github.com/xor2k/npy-append-array
License-File: LICENSE
Dynamic: license-file
